nagooglesearch/__init__.py
nagooglesearch/nagooglesearch.py
nagooglesearch-8.2.dist-info/METADATA
nagooglesearch-8.2.dist-info/WHEEL
nagooglesearch-8.2.dist-info/top_level.txt
nagooglesearch-8.2.dist-info/RECORD
