Metadata-Version: 2.4
Name: nagooglesearch
Version: 8.2
Summary: Not another Google searching tool.
Author: Ivan Sincek
Project-URL: Homepage, https://github.com/ivan-sincek/nagooglesearch
Classifier: Programming Language :: Python :: 3
Classifier: License :: OSI Approved :: MIT License
Classifier: Operating System :: OS Independent
Requires-Python: >=3.10
Requires-Dist: bot_safe_agents>=1.0
Requires-Dist: requests>=2.31.0
Requires-Dist: bs4>=0.0.1
Requires-Dist: beautifulsoup4>=4.12.3
